comfy/__init__.py
comfy/clip.py
comfy/conditioning.py
comfy/latent_image.py
comfy/stable_diffusion.py
comfy/util.py
comfy/vae.py
comfy/configs/anything_v3.yaml
comfy/configs/v1-inference.yaml
comfy/configs/v1-inference_clip_skip_2.yaml
comfy/configs/v1-inference_clip_skip_2_fp16.yaml
comfy/configs/v1-inference_fp16.yaml
comfy/configs/v1-inpainting-inference.yaml
comfy/configs/v2-inference-v.yaml
comfy/configs/v2-inference-v_fp32.yaml
comfy/configs/v2-inference.yaml
comfy/configs/v2-inference_fp32.yaml
comfy/configs/v2-inpainting-inference.yaml
comfy/hazard/__init__.py
comfy/hazard/model_management.py
comfy/hazard/nodes.py
comfy/hazard/samplers.py
comfy/hazard/sd.py
comfy/hazard/sd1_clip.py
comfy/hazard/sd1_clip_config.json
comfy/hazard/sd2_clip.py
comfy/hazard/sd2_clip_config.json
comfy/hazard/utils.py
comfy/hazard/cldm/__init__.py
comfy/hazard/cldm/cldm.py
comfy/hazard/extra_samplers/__init__.py
comfy/hazard/extra_samplers/uni_pc.py
comfy/hazard/k_diffusion/__init__.py
comfy/hazard/k_diffusion/augmentation.py
comfy/hazard/k_diffusion/config.py
comfy/hazard/k_diffusion/evaluation.py
comfy/hazard/k_diffusion/external.py
comfy/hazard/k_diffusion/gns.py
comfy/hazard/k_diffusion/layers.py
comfy/hazard/k_diffusion/sampling.py
comfy/hazard/k_diffusion/utils.py
comfy/hazard/k_diffusion/models/__init__.py
comfy/hazard/k_diffusion/models/image_v1.py
comfy/hazard/ldm/__init__.py
comfy/hazard/ldm/util.py
comfy/hazard/ldm/data/__init__.py
comfy/hazard/ldm/data/util.py
comfy/hazard/ldm/models/__init__.py
comfy/hazard/ldm/models/autoencoder.py
comfy/hazard/ldm/models/diffusion/__init__.py
comfy/hazard/ldm/models/diffusion/ddim.py
comfy/hazard/ldm/models/diffusion/ddpm.py
comfy/hazard/ldm/models/diffusion/plms.py
comfy/hazard/ldm/models/diffusion/sampling_util.py
comfy/hazard/ldm/models/diffusion/dpm_solver/__init__.py
comfy/hazard/ldm/models/diffusion/dpm_solver/dpm_solver.py
comfy/hazard/ldm/models/diffusion/dpm_solver/sampler.py
comfy/hazard/ldm/modules/__init__.py
comfylib-0.0.5.dist-info/LICENSE
comfylib-0.0.5.dist-info/METADATA
comfylib-0.0.5.dist-info/WHEEL
comfylib-0.0.5.dist-info/top_level.txt
comfylib-0.0.5.dist-info/RECORD
