Metadata-Version: 2.1
Name: comfylib
Version: 0.0.5
Summary: Stable Diffusion library, based on the implementation in ComfyUI
Author: comfyanonymous
Author-email: Alex Dodge <alexdodge@gmail.com>
Project-URL: Library Homepage, https://github.com/adodge/ComfyLib
Project-URL: Library Bug Tracker, https://github.com/adodge/ComfyLib/issues
Project-URL: Original Project Homepage, https://github.com/comfyanonymous/ComfyUI
Keywords: stable diffusion
Classifier: Development Status :: 2 - Pre-Alpha
Classifier: Programming Language :: Python :: 3
Classifier: License :: OSI Approved :: GNU General Public License v3 (GPLv3)
Requires-Python: >=3.9
License-File: LICENSE
Requires-Dist: torch
Requires-Dist: torchdiffeq
Requires-Dist: torchsde
Requires-Dist: omegaconf
Requires-Dist: einops
Requires-Dist: open-clip-torch
Requires-Dist: transformers
Requires-Dist: safetensors
Requires-Dist: pytorch-lightning
Requires-Dist: accelerate
Requires-Dist: Pillow
Requires-Dist: numpy
